[
  {
    "text": "The man who makes no mistakes does not usually make anything.",
    "source": "Phelps, inspired by Ancient Greek wisdom",
    "difficulty": "Easy",
    "category": "Greek Wisdom",
    "origin": "Ancient Greece"
  },
  {
    "text": "Better to do a little well, than a great deal badly.",
    "source": "Socrates",
    "difficulty": "Easy",
    "category": "Greek Philosophy",
    "origin": "Ancient Greece"
  },
  {
    "text": "The secret of change is to focus all of your energy, not on fighting the old, but on building the new.",
    "source": "Socrates",
    "difficulty": "Medium",
    "category": "Greek Philosophy",
    "origin": "Ancient Greece"
  },
  {
    "text": "To avoid criticism say nothing, do nothing, be nothing.",
    "source": "Aristotle",
    "difficulty": "Medium",
    "category": "Greek Philosophy",
    "origin": "Ancient Greece"
  }
] 