[
  {
    "text": "The Tripitaka",
    "source": "Buddhist Sacred Text",
    "difficulty": "Medium",
    "category": "SacredTextsTripitaka",
    "origin": "South Asia"
  },
  {
    "text": "Peace comes from within. Do not seek it without.",
    "source": "Buddha, Dhammapada",
    "difficulty": "Easy",
    "category": "SacredTextsTripitaka",
    "origin": "Ancient India"
  },
  {
    "text": "Three things cannot be long hidden: the sun, the moon, and the truth.",
    "source": "Buddha, Dhammapada",
    "difficulty": "Easy",
    "category": "SacredTextsTripitaka",
    "origin": "Ancient India"
  },
  {
    "text": "The mind is everything. What you think you become.",
    "source": "Buddha, Dhammapada",
    "difficulty": "Medium",
    "category": "SacredTextsTripitaka",
    "origin": "Ancient India"
  },
  {
    "text": "No one saves us but ourselves. No one can and no one may. We ourselves must walk the path.",
    "source": "Buddha, Dhammapada",
    "difficulty": "Medium",
    "category": "SacredTextsTripitaka",
    "origin": "Ancient India"
  },
  {
    "text": "Holding on to anger is like grasping a hot coal with the intent of throwing it at someone else; you are the one who gets burned.",
    "source": "Buddha, Dhammapada",
    "difficulty": "Medium",
    "category": "SacredTextsTripitaka",
    "origin": "Ancient India"
  },
  {
    "text": "Hatred does not cease by hatred, but only by love; this is the eternal rule.",
    "source": "Buddha, Dhammapada",
    "difficulty": "Medium",
    "category": "SacredTextsTripitaka",
    "origin": "Ancient India"
  },
  {
    "text": "Better than a thousand hollow words, is one word that brings peace.",
    "source": "Buddha, Dhammapada",
    "difficulty": "Easy",
    "category": "SacredTextsTripitaka",
    "origin": "Ancient India"
  },
  {
    "text": "Your work is to discover your work and then with all your heart to give yourself to it.",
    "source": "Buddha, Dhammapada",
    "difficulty": "Medium",
    "category": "SacredTextsTripitaka",
    "origin": "Ancient India"
  },
  {
    "text": "Do not dwell in the past, do not dream of the future, concentrate the mind on the present moment.",
    "source": "Buddha, Dhammapada",
    "difficulty": "Medium",
    "category": "SacredTextsTripitaka",
    "origin": "Ancient India"
  },
  {
    "text": "If a man's thoughts are muddy, If he is reckless and full of deceit, How can he wear the yellow robe? Whoever is master of his own nature, Bright, clear and true, He may indeed wear the yellow robe.",
    "source": "Buddha, Dhammapada",
    "difficulty": "Hard",
    "category": "SacredTextsTripitaka",
    "origin": "Ancient India"
  }
] 